Metadata-Version: 2.1
Name: pywand
Version: 0.1.1
Summary: Read IR codes from MagiQuest Wands
Home-page: https://gitlab.com/rveach/wand
Author: Ryan Veach
Author-email: rveach@gmail.com
License: MIT
Download-URL: https://gitlab.com/rveach/wand/-/archive/master/wand-master.tar.gz
Keywords: wand,magiquest,IR
Platform: UNKNOWN
Classifier: Development Status :: 3 - Alpha
Classifier: Intended Audience :: Developers
Classifier: License :: OSI Approved :: MIT License
Classifier: Natural Language :: English
Classifier: Operating System :: POSIX :: Linux
Classifier: Programming Language :: Python :: 3
Classifier: Topic :: Software Development :: Libraries
Requires-Python: >=3.5
